CP0_Reg.v
`timescale 1ns / 1ps
//////////////////////////////////////////////////////////////////////////////////
// Module Name: CP0_Reg
// Description: CP0协处理器寄存器 - 异常处理和特权指令支持
//////////////////////////////////////////////////////////////////////////////////

module CP0_Reg (
    input         clk,
    input         rst,

    // 读写接口 (MFC0/MTCO指令)
    input         we,          // 写使能 <- MTC0
    input  [4:0]  addr,        // 寄存器地址
    input  [31:0] wdata,       // 写入数据
    output reg [31:0] rdata,       // 读取数据 -> MFC0

    // verilator lint_off UNUSEDSIGNAL
    // 异常处理接口
    input         eret,        // ERET信号 <- Control
    input  [31:0] epc_i,       // EPC输入 <- 流水线(异常指令地址)
    input  [5:0]  cause_i,     // 异常原因 <- Trap_Detect
    input         syscall_i,   // SYSCALL <- Trap_Detect
    input         break_i,     // BREAK <- Trap_Detect

    // 输出接口
    output [31:0] epc_o,       // EPC输出 -> PC_Mux
    output [5:0]  cause_o,     // 异常原因输出 (ExcCode字段)
    output        exception_o  // 异常发生信号 -> 流水线
);

    // CP0寄存器地址 (来自3-4对接_1.md)
    localparam ADDR_BADVADDR = 5'd8;   // BadVAddr - 错误虚拟地址
    localparam ADDR_COUNT    = 5'd9;   // Count - 计数器
    localparam ADDR_STATUS   = 5'd12;  // Status - 状态寄存器
    localparam ADDR_CAUSE    = 5'd13;  // Cause - 异常原因
    localparam ADDR_EPC      = 5'd14;  // EPC - 异常程序计数器

    // 异常发生条件
    wire exception = syscall_i || break_i;

    // 异常类型 (trap_cause)
    wire [5:0] trap_cause = syscall_i ? 6'd8 :   // Sys = 8
                           break_i  ? 6'd9 :    // Bp = 9
                           cause_i;              // 其他异常

    // EPC寄存器
    reg [31:0] epc_reg;
    always @(posedge clk or posedge rst) begin
        if (rst) begin
            epc_reg <= 32'd0;
        end else if (exception) begin
            epc_reg <= epc_i;  // 保存异常指令地址
        end else if (we && addr == ADDR_EPC) begin
            epc_reg <= wdata;  // MTC0手动写EPC
        end
    end

    // Cause寄存器 (只写，保存异常原因)
    reg [31:0] cause_reg;
    always @(posedge clk or posedge rst) begin
        if (rst) begin
            cause_reg <= 32'd0;
        end else if (exception) begin
            // Cause = {26'd0, trap_cause, 5'd0}
            cause_reg <= {26'd0, trap_cause};
        end else if (we && addr == ADDR_CAUSE) begin
            cause_reg <= wdata;  // MTC0手动写Cause
        end
    end

    // Status寄存器 (简化版)
    reg [31:0] status_reg;
    always @(posedge clk or posedge rst) begin
        if (rst) begin
            status_reg <= 32'd0;
        end else if (we && addr == ADDR_STATUS) begin
            status_reg <= wdata;  // MTC0手动写Status
        end
    end

    // Count寄存器 (简化计数器)
    reg [31:0] count_reg;
    always @(posedge clk or posedge rst) begin
        if (rst) begin
            count_reg <= 32'd0;
        end else begin
            count_reg <= count_reg + 32'd1;
        end
    end

    // BadVAddr寄存器 (简化，保存错误地址)
    reg [31:0] badvaddr_reg;
    always @(posedge clk or posedge rst) begin
        if (rst) begin
            badvaddr_reg <= 32'd0;
        end else if (exception) begin
            badvaddr_reg <= epc_i;  // 简化：保存PC
        end
    end

    // 读数据多路选择 (MFC0)
    always @(*) begin
        case (addr)
            ADDR_BADVADDR: rdata = badvaddr_reg;
            ADDR_COUNT:    rdata = count_reg;
            ADDR_STATUS:   rdata = status_reg;
            ADDR_CAUSE:    rdata = cause_reg;
            ADDR_EPC:      rdata = epc_reg;
            default:       rdata = 32'd0;
        endcase
    end

    // 输出信号
    assign epc_o = epc_reg;
    assign cause_o = cause_reg[5:0];  // ExcCode字段 (低6位)
    assign exception_o = exception;

endmodule

cp0_reg_waveform.vcd
$version Generated by VerilatedVcd $end
$date Sun Jan 25 22:24:26 2026 $end
$timescale 1ps $end

 $scope module TOP $end
  $var wire  5 + addr [4:0] $end
  $var wire  1 2 break_i $end
  $var wire  6 0 cause_i [5:0] $end
  $var wire  6 4 cause_o [5:0] $end
  $var wire  1 ( clk $end
  $var wire 32 / epc_i [31:0] $end
  $var wire 32 3 epc_o [31:0] $end
  $var wire  1 . eret $end
  $var wire  1 5 exception_o $end
  $var wire 32 - rdata [31:0] $end
  $var wire  1 ) rst $end
  $var wire  1 1 syscall_i $end
  $var wire 32 , wdata [31:0] $end
  $var wire  1 * we $end
  $scope module CP0_Reg $end
   $var wire  5 7 ADDR_BADVADDR [4:0] $end
   $var wire  5 : ADDR_CAUSE [4:0] $end
   $var wire  5 8 ADDR_COUNT [4:0] $end
   $var wire  5 ; ADDR_EPC [4:0] $end
   $var wire  5 9 ADDR_STATUS [4:0] $end
   $var wire  5 + addr [4:0] $end
   $var wire 32 ' badvaddr_reg [31:0] $end
   $var wire  1 2 break_i $end
   $var wire  6 0 cause_i [5:0] $end
   $var wire  6 4 cause_o [5:0] $end
   $var wire 32 $ cause_reg [31:0] $end
   $var wire  1 ( clk $end
   $var wire 32 & count_reg [31:0] $end
   $var wire 32 / epc_i [31:0] $end
   $var wire 32 3 epc_o [31:0] $end
   $var wire 32 # epc_reg [31:0] $end
   $var wire  1 . eret $end
   $var wire  1 5 exception $end
   $var wire  1 5 exception_o $end
   $var wire 32 - rdata [31:0] $end
   $var wire  1 ) rst $end
   $var wire 32 % status_reg [31:0] $end
   $var wire  1 1 syscall_i $end
   $var wire  6 6 trap_cause [5:0] $end
   $var wire 32 , wdata [31:0] $end
   $var wire  1 * we $end
  $upscope $end
 $upscope $end
$enddefinitions $end


#0
b00000000000000000000000000000000 #
b00000000000000000000000000000000 $
b00000000000000000000000000000000 %
b00000000000000000000000000000000 &
b00000000000000000000000000000000 '
0(
1)
0*
b00000 +
b00000000000000000000000000000000 ,
b00000000000000000000000000000000 -
0.
b00000000000000000000000000000000 /
b000000 0
01
02
b00000000000000000000000000000000 3
b000000 4
05
b000000 6
b01000 7
b01001 8
b01100 9
b01101 :
b01110 ;
#5
0)
#10
b00000000010000000000000000100000 #
b00000000000000000000000000001000 $
b00000000000000000000000000000001 &
b00000000010000000000000000100000 '
1(
b00000000010000000000000000100000 /
11
b00000000010000000000000000100000 3
15
b001000 6
#15
0(
#20
b00000000010000000000000000110000 #
b00000000000000000000000000001001 $
b00000000000000000000000000000010 &
b00000000010000000000000000110000 '
1(
b00000000010000000000000000110000 /
01
12
b00000000010000000000000000110000 3
b001001 6
#25
0(
#30
b00000000000000000000000000001000 $
b00000000000000000000000000000011 &
1(
11
02
b001000 6
#35
0(
#40
b00010010001101000101011001111000 #
b00000000000000000000000000000100 &
1(
1*
b01110 +
b00010010001101000101011001111000 ,
b00010010001101000101011001111000 -
01
b00010010001101000101011001111000 3
05
b000000 6
#45
0(
#50
0*
b01001 +
b00000000000000000000000000000100 -
#60
#70
b00000000000000000000000000000001 %
b00000000000000000000000000000101 &
1(
1*
b01100 +
b00000000000000000000000000000001 ,
b00000000000000000000000000000001 -
#75
0(
#80
0*
#90
b00000000000000000001001000110100 $
b00000000000000000000000000000110 &
1(
1*
b01101 +
b00000000000000000001001000110100 ,
b00000000000000000001001000110100 -
b100011 4
#95
0(
#100
0*
